mkdocs_external_import/__init__.py
mkdocs_external_import/external_import.py
mkdocs_external_import-0.0.1.dist-info/LICENSE
mkdocs_external_import-0.0.1.dist-info/METADATA
mkdocs_external_import-0.0.1.dist-info/WHEEL
mkdocs_external_import-0.0.1.dist-info/entry_points.txt
mkdocs_external_import-0.0.1.dist-info/RECORD
