Metadata-Version: 2.1
Name: mkdocs-external-import
Version: 0.0.1
Summary: Import external markdown files into your documentation site.
License: MPL-2.0
Author: Lawrence
Author-email: lawrence@acode.ninja
Requires-Python: >=3.11,<4.0
Classifier: License :: OSI Approved
Classifier: Programming Language :: Python :: 3
Classifier: Programming Language :: Python :: 3.11
Classifier: Programming Language :: Python :: 3.12
Requires-Dist: mkdocs (>=1.5.2,<2.0.0)
Requires-Dist: requests (>=2.31.0,<3.0.0)
